alephclient/__init__.py
alephclient/api.py
alephclient/cli.py
alephclient/crawldir.py
alephclient/errors.py
alephclient/fetchdir.py
alephclient/settings.py
alephclient/util.py
alephclient-2.6.0.dist-info/LICENSE
alephclient-2.6.0.dist-info/METADATA
alephclient-2.6.0.dist-info/WHEEL
alephclient-2.6.0.dist-info/entry_points.txt
alephclient-2.6.0.dist-info/top_level.txt
alephclient-2.6.0.dist-info/RECORD
