Metadata-Version: 2.1
Name: alephclient
Version: 2.6.0
Summary: Command-line client for Aleph API
Home-page: http://github.com/alephdata/alephclient
Author: Organized Crime and Corruption Reporting Project
Author-email: data@occrp.org
License: MIT
Classifier: Intended Audience :: Developers
Classifier: Operating System :: OS Independent
Classifier: Programming Language :: Python
Classifier: Programming Language :: Python :: 3.6
Classifier: Programming Language :: Python :: 3.7
License-File: LICENSE
Requires-Dist: banal>=1.0.1
Requires-Dist: pyyaml
Requires-Dist: requests>=2.21.0
Requires-Dist: requests-toolbelt>=0.9.1
Requires-Dist: click>=7.0
Provides-Extra: dev
Requires-Dist: mypy; extra == "dev"
Requires-Dist: wheel; extra == "dev"
Requires-Dist: pytest; extra == "dev"
Requires-Dist: pytest-mock>=1.10.0; extra == "dev"
Requires-Dist: types-requests; extra == "dev"
Requires-Dist: types-setuptools; extra == "dev"
